{
  "id": "e2f5b544-c3c8-4d8c-91ed-c8424defee56",
  "prevId": "6a6948ed-7284-458e-a32c-50802daf9c5a",
  "version": "7",
  "dialect": "postgresql",
  "tables": {
    "auth.users": {
      "name": "users",
      "schema": "auth",
      "columns": {
        "id": {
          "name": "id",
          "type": "uuid",
          "primaryKey": true,
          "notNull": true
        },
        "email": {
          "name": "email",
          "type": "varchar",
          "primaryKey": false,
          "notNull": false
        },
        "email_confirmed_at": {
          "name": "email_confirmed_at",
          "type": "timestamp",
          "primaryKey": false,
          "notNull": false
        },
        "last_sign_in_at": {
          "name": "last_sign_in_at",
          "type": "timestamp",
          "primaryKey": false,
          "notNull": false
        },
        "banned_until": {
          "name": "banned_until",
          "type": "timestamp",
          "primaryKey": false,
          "notNull": false
        },
        "updated_at": {
          "name": "updated_at",
          "type": "timestamp",
          "primaryKey": false,
          "notNull": false
        },
        "created_at": {
          "name": "created_at",
          "type": "timestamp",
          "primaryKey": false,
          "notNull": true,
          "default": "now()"
        },
        "deleted_at": {
          "name": "deleted_at",
          "type": "timestamp",
          "primaryKey": false,
          "notNull": false
        }
      },
      "indexes": {},
      "foreignKeys": {},
      "compositePrimaryKeys": {},
      "uniqueConstraints": {},
      "policies": {},
      "checkConstraints": {},
      "isRLSEnabled": false
    },
    "public.business_infos": {
      "name": "business_infos",
      "schema": "",
      "columns": {
        "id": {
          "name": "id",
          "type": "uuid",
          "primaryKey": true,
          "notNull": true,
          "default": "gen_random_uuid()"
        },
        "name_corporate_reason": {
          "name": "name_corporate_reason",
          "type": "text",
          "primaryKey": false,
          "notNull": true
        },
        "cnpj_cpf": {
          "name": "cnpj_cpf",
          "type": "text",
          "primaryKey": false,
          "notNull": true
        },
        "email": {
          "name": "email",
          "type": "text",
          "primaryKey": false,
          "notNull": false
        },
        "phone_fax": {
          "name": "phone_fax",
          "type": "text",
          "primaryKey": false,
          "notNull": false
        },
        "contact": {
          "name": "contact",
          "type": "text",
          "primaryKey": false,
          "notNull": false
        },
        "state_registration": {
          "name": "state_registration",
          "type": "text",
          "primaryKey": false,
          "notNull": false
        },
        "trade_name": {
          "name": "trade_name",
          "type": "text",
          "primaryKey": false,
          "notNull": false
        },
        "modification_date": {
          "name": "modification_date",
          "type": "text",
          "primaryKey": false,
          "notNull": false
        },
        "updated_at": {
          "name": "updated_at",
          "type": "timestamp",
          "primaryKey": false,
          "notNull": false
        },
        "created_at": {
          "name": "created_at",
          "type": "timestamp",
          "primaryKey": false,
          "notNull": true,
          "default": "now()"
        },
        "deleted_at": {
          "name": "deleted_at",
          "type": "timestamp",
          "primaryKey": false,
          "notNull": false
        }
      },
      "indexes": {},
      "foreignKeys": {},
      "compositePrimaryKeys": {},
      "uniqueConstraints": {},
      "policies": {},
      "checkConstraints": {},
      "isRLSEnabled": false
    },
    "public.financial_calculations": {
      "name": "financial_calculations",
      "schema": "",
      "columns": {
        "id": {
          "name": "id",
          "type": "uuid",
          "primaryKey": true,
          "notNull": true,
          "default": "gen_random_uuid()"
        },
        "icms_base": {
          "name": "icms_base",
          "type": "numeric",
          "primaryKey": false,
          "notNull": true
        },
        "icms_value": {
          "name": "icms_value",
          "type": "numeric",
          "primaryKey": false,
          "notNull": true
        },
        "st_icms_base": {
          "name": "st_icms_base",
          "type": "numeric",
          "primaryKey": false,
          "notNull": true
        },
        "st_icms_value": {
          "name": "st_icms_value",
          "type": "numeric",
          "primaryKey": false,
          "notNull": true
        },
        "fcp_value": {
          "name": "fcp_value",
          "type": "numeric",
          "primaryKey": false,
          "notNull": true
        },
        "pis_value": {
          "name": "pis_value",
          "type": "numeric",
          "primaryKey": false,
          "notNull": true
        },
        "total_product_value": {
          "name": "total_product_value",
          "type": "numeric",
          "primaryKey": false,
          "notNull": true
        },
        "freight_value": {
          "name": "freight_value",
          "type": "numeric",
          "primaryKey": false,
          "notNull": true
        },
        "insurance_value": {
          "name": "insurance_value",
          "type": "numeric",
          "primaryKey": false,
          "notNull": true
        },
        "discount": {
          "name": "discount",
          "type": "numeric",
          "primaryKey": false,
          "notNull": true
        },
        "other_expenses": {
          "name": "other_expenses",
          "type": "numeric",
          "primaryKey": false,
          "notNull": true
        },
        "ipi_value": {
          "name": "ipi_value",
          "type": "numeric",
          "primaryKey": false,
          "notNull": true
        },
        "cofins_value": {
          "name": "cofins_value",
          "type": "numeric",
          "primaryKey": false,
          "notNull": true
        },
        "total_invoice_value": {
          "name": "total_invoice_value",
          "type": "numeric",
          "primaryKey": false,
          "notNull": true
        },
        "updated_at": {
          "name": "updated_at",
          "type": "timestamp",
          "primaryKey": false,
          "notNull": false
        },
        "created_at": {
          "name": "created_at",
          "type": "timestamp",
          "primaryKey": false,
          "notNull": true,
          "default": "now()"
        },
        "deleted_at": {
          "name": "deleted_at",
          "type": "timestamp",
          "primaryKey": false,
          "notNull": false
        }
      },
      "indexes": {},
      "foreignKeys": {},
      "compositePrimaryKeys": {},
      "uniqueConstraints": {},
      "policies": {},
      "checkConstraints": {},
      "isRLSEnabled": false
    },
    "public.locations": {
      "name": "locations",
      "schema": "",
      "columns": {
        "id": {
          "name": "id",
          "type": "uuid",
          "primaryKey": true,
          "notNull": true,
          "default": "gen_random_uuid()"
        },
        "route": {
          "name": "route",
          "type": "varchar(256)",
          "primaryKey": false,
          "notNull": true
        },
        "subpremise": {
          "name": "subpremise",
          "type": "text",
          "primaryKey": false,
          "notNull": false
        },
        "street_number": {
          "name": "street_number",
          "type": "text",
          "primaryKey": false,
          "notNull": true
        },
        "sublocality": {
          "name": "sublocality",
          "type": "text",
          "primaryKey": false,
          "notNull": true
        },
        "locality": {
          "name": "locality",
          "type": "varchar(100)",
          "primaryKey": false,
          "notNull": true
        },
        "administrative_area_level_1": {
          "name": "administrative_area_level_1",
          "type": "text",
          "primaryKey": false,
          "notNull": true
        },
        "administrative_area_level_2": {
          "name": "administrative_area_level_2",
          "type": "text",
          "primaryKey": false,
          "notNull": false
        },
        "country": {
          "name": "country",
          "type": "text",
          "primaryKey": false,
          "notNull": true
        },
        "formatted_address": {
          "name": "formatted_address",
          "type": "text",
          "primaryKey": false,
          "notNull": true
        },
        "postalCode": {
          "name": "postalCode",
          "type": "varchar(20)",
          "primaryKey": false,
          "notNull": true
        },
        "updated_at": {
          "name": "updated_at",
          "type": "timestamp",
          "primaryKey": false,
          "notNull": false
        },
        "created_at": {
          "name": "created_at",
          "type": "timestamp",
          "primaryKey": false,
          "notNull": true,
          "default": "now()"
        },
        "deleted_at": {
          "name": "deleted_at",
          "type": "timestamp",
          "primaryKey": false,
          "notNull": false
        }
      },
      "indexes": {
        "postal_code_idx": {
          "name": "postal_code_idx",
          "columns": [
            {
              "expression": "postalCode",
              "isExpression": false,
              "asc": true,
              "nulls": "last"
            }
          ],
          "isUnique": false,
          "concurrently": false,
          "method": "btree",
          "with": {}
        },
        "locality_idx": {
          "name": "locality_idx",
          "columns": [
            {
              "expression": "locality",
              "isExpression": false,
              "asc": true,
              "nulls": "last"
            }
          ],
          "isUnique": false,
          "concurrently": false,
          "method": "btree",
          "with": {}
        },
        "route_idx": {
          "name": "route_idx",
          "columns": [
            {
              "expression": "route",
              "isExpression": false,
              "asc": true,
              "nulls": "last"
            }
          ],
          "isUnique": false,
          "concurrently": false,
          "method": "btree",
          "with": {}
        },
        "administrative_area_idx": {
          "name": "administrative_area_idx",
          "columns": [
            {
              "expression": "locality",
              "isExpression": false,
              "asc": true,
              "nulls": "last"
            },
            {
              "expression": "administrative_area_level_1",
              "isExpression": false,
              "asc": true,
              "nulls": "last"
            },
            {
              "expression": "country",
              "isExpression": false,
              "asc": true,
              "nulls": "last"
            }
          ],
          "isUnique": false,
          "concurrently": false,
          "method": "btree",
          "with": {}
        }
      },
      "foreignKeys": {},
      "compositePrimaryKeys": {},
      "uniqueConstraints": {},
      "policies": {},
      "checkConstraints": {},
      "isRLSEnabled": false
    },
    "public.orders": {
      "name": "orders",
      "schema": "",
      "columns": {
        "id": {
          "name": "id",
          "type": "uuid",
          "primaryKey": true,
          "notNull": true,
          "default": "gen_random_uuid()"
        },
        "code_reference": {
          "name": "code_reference",
          "type": "text",
          "primaryKey": false,
          "notNull": true
        },
        "updated_at": {
          "name": "updated_at",
          "type": "timestamp",
          "primaryKey": false,
          "notNull": false
        },
        "created_at": {
          "name": "created_at",
          "type": "timestamp",
          "primaryKey": false,
          "notNull": true,
          "default": "now()"
        },
        "deleted_at": {
          "name": "deleted_at",
          "type": "timestamp",
          "primaryKey": false,
          "notNull": false
        }
      },
      "indexes": {},
      "foreignKeys": {},
      "compositePrimaryKeys": {},
      "uniqueConstraints": {
        "orders_code_reference_unique": {
          "name": "orders_code_reference_unique",
          "nullsNotDistinct": false,
          "columns": [
            "code_reference"
          ]
        }
      },
      "policies": {},
      "checkConstraints": {},
      "isRLSEnabled": false
    },
    "public.shipment_items_to_orders": {
      "name": "shipment_items_to_orders",
      "schema": "",
      "columns": {
        "shipment_item_id": {
          "name": "shipment_item_id",
          "type": "uuid",
          "primaryKey": false,
          "notNull": true
        },
        "order_id": {
          "name": "order_id",
          "type": "uuid",
          "primaryKey": false,
          "notNull": true
        },
        "updated_at": {
          "name": "updated_at",
          "type": "timestamp",
          "primaryKey": false,
          "notNull": false
        },
        "created_at": {
          "name": "created_at",
          "type": "timestamp",
          "primaryKey": false,
          "notNull": true,
          "default": "now()"
        },
        "deleted_at": {
          "name": "deleted_at",
          "type": "timestamp",
          "primaryKey": false,
          "notNull": false
        }
      },
      "indexes": {
        "shipment_item_to_order_shipment_item_id_idx": {
          "name": "shipment_item_to_order_shipment_item_id_idx",
          "columns": [
            {
              "expression": "shipment_item_id",
              "isExpression": false,
              "asc": true,
              "nulls": "last"
            }
          ],
          "isUnique": false,
          "concurrently": false,
          "method": "btree",
          "with": {}
        },
        "shipment_item_to_order_order_id_idx": {
          "name": "shipment_item_to_order_order_id_idx",
          "columns": [
            {
              "expression": "order_id",
              "isExpression": false,
              "asc": true,
              "nulls": "last"
            }
          ],
          "isUnique": false,
          "concurrently": false,
          "method": "btree",
          "with": {}
        }
      },
      "foreignKeys": {
        "shipment_items_to_orders_shipment_item_id_shipment_items_id_fk": {
          "name": "shipment_items_to_orders_shipment_item_id_shipment_items_id_fk",
          "tableFrom": "shipment_items_to_orders",
          "tableTo": "shipment_items",
          "columnsFrom": [
            "shipment_item_id"
          ],
          "columnsTo": [
            "id"
          ],
          "onDelete": "cascade",
          "onUpdate": "no action"
        },
        "shipment_items_to_orders_order_id_orders_id_fk": {
          "name": "shipment_items_to_orders_order_id_orders_id_fk",
          "tableFrom": "shipment_items_to_orders",
          "tableTo": "orders",
          "columnsFrom": [
            "order_id"
          ],
          "columnsTo": [
            "id"
          ],
          "onDelete": "cascade",
          "onUpdate": "no action"
        }
      },
      "compositePrimaryKeys": {
        "shipment_items_to_orders_shipment_item_id_order_id_pk": {
          "name": "shipment_items_to_orders_shipment_item_id_order_id_pk",
          "columns": [
            "shipment_item_id",
            "order_id"
          ]
        }
      },
      "uniqueConstraints": {},
      "policies": {},
      "checkConstraints": {},
      "isRLSEnabled": false
    },
    "public.shipments_to_orders": {
      "name": "shipments_to_orders",
      "schema": "",
      "columns": {
        "shipment_id": {
          "name": "shipment_id",
          "type": "uuid",
          "primaryKey": false,
          "notNull": true
        },
        "order_id": {
          "name": "order_id",
          "type": "uuid",
          "primaryKey": false,
          "notNull": true
        },
        "updated_at": {
          "name": "updated_at",
          "type": "timestamp",
          "primaryKey": false,
          "notNull": false
        },
        "created_at": {
          "name": "created_at",
          "type": "timestamp",
          "primaryKey": false,
          "notNull": true,
          "default": "now()"
        },
        "deleted_at": {
          "name": "deleted_at",
          "type": "timestamp",
          "primaryKey": false,
          "notNull": false
        }
      },
      "indexes": {
        "shipments_to_order_shipment_id_idx": {
          "name": "shipments_to_order_shipment_id_idx",
          "columns": [
            {
              "expression": "shipment_id",
              "isExpression": false,
              "asc": true,
              "nulls": "last"
            }
          ],
          "isUnique": false,
          "concurrently": false,
          "method": "btree",
          "with": {}
        },
        "shipments_to_order_order_id_idx": {
          "name": "shipments_to_order_order_id_idx",
          "columns": [
            {
              "expression": "order_id",
              "isExpression": false,
              "asc": true,
              "nulls": "last"
            }
          ],
          "isUnique": false,
          "concurrently": false,
          "method": "btree",
          "with": {}
        }
      },
      "foreignKeys": {
        "shipments_to_orders_shipment_id_shipments_id_fk": {
          "name": "shipments_to_orders_shipment_id_shipments_id_fk",
          "tableFrom": "shipments_to_orders",
          "tableTo": "shipments",
          "columnsFrom": [
            "shipment_id"
          ],
          "columnsTo": [
            "id"
          ],
          "onDelete": "cascade",
          "onUpdate": "no action"
        },
        "shipments_to_orders_order_id_orders_id_fk": {
          "name": "shipments_to_orders_order_id_orders_id_fk",
          "tableFrom": "shipments_to_orders",
          "tableTo": "orders",
          "columnsFrom": [
            "order_id"
          ],
          "columnsTo": [
            "id"
          ],
          "onDelete": "cascade",
          "onUpdate": "no action"
        }
      },
      "compositePrimaryKeys": {
        "shipments_to_orders_shipment_id_order_id_pk": {
          "name": "shipments_to_orders_shipment_id_order_id_pk",
          "columns": [
            "shipment_id",
            "order_id"
          ]
        }
      },
      "uniqueConstraints": {},
      "policies": {},
      "checkConstraints": {},
      "isRLSEnabled": false
    },
    "public.permissions": {
      "name": "permissions",
      "schema": "",
      "columns": {
        "id": {
          "name": "id",
          "type": "integer",
          "primaryKey": true,
          "notNull": true,
          "identity": {
            "type": "always",
            "name": "permissions_id_seq",
            "schema": "public",
            "increment": "1",
            "startWith": "1",
            "minValue": "1",
            "maxValue": "2147483647",
            "cache": "1",
            "cycle": false
          }
        },
        "role": {
          "name": "role",
          "type": "text",
          "primaryKey": false,
          "notNull": true
        },
        "parent_id": {
          "name": "parent_id",
          "type": "integer",
          "primaryKey": false,
          "notNull": false
        }
      },
      "indexes": {
        "parent_idx": {
          "name": "parent_idx",
          "columns": [
            {
              "expression": "parent_id",
              "isExpression": false,
              "asc": true,
              "nulls": "last"
            }
          ],
          "isUnique": false,
          "concurrently": false,
          "method": "btree",
          "with": {}
        }
      },
      "foreignKeys": {
        "permissions_parent_id_permissions_id_fk": {
          "name": "permissions_parent_id_permissions_id_fk",
          "tableFrom": "permissions",
          "tableTo": "permissions",
          "columnsFrom": [
            "parent_id"
          ],
          "columnsTo": [
            "id"
          ],
          "onDelete": "no action",
          "onUpdate": "no action"
        }
      },
      "compositePrimaryKeys": {},
      "uniqueConstraints": {
        "permissions_role_unique": {
          "name": "permissions_role_unique",
          "nullsNotDistinct": false,
          "columns": [
            "role"
          ]
        }
      },
      "policies": {},
      "checkConstraints": {},
      "isRLSEnabled": false
    },
    "public.role_to_permissions": {
      "name": "role_to_permissions",
      "schema": "",
      "columns": {
        "role_id": {
          "name": "role_id",
          "type": "integer",
          "primaryKey": false,
          "notNull": true
        },
        "permission_id": {
          "name": "permission_id",
          "type": "integer",
          "primaryKey": false,
          "notNull": true
        }
      },
      "indexes": {},
      "foreignKeys": {
        "role_to_permissions_role_id_roles_id_fk": {
          "name": "role_to_permissions_role_id_roles_id_fk",
          "tableFrom": "role_to_permissions",
          "tableTo": "roles",
          "columnsFrom": [
            "role_id"
          ],
          "columnsTo": [
            "id"
          ],
          "onDelete": "no action",
          "onUpdate": "no action"
        },
        "role_to_permissions_permission_id_permissions_id_fk": {
          "name": "role_to_permissions_permission_id_permissions_id_fk",
          "tableFrom": "role_to_permissions",
          "tableTo": "permissions",
          "columnsFrom": [
            "permission_id"
          ],
          "columnsTo": [
            "id"
          ],
          "onDelete": "no action",
          "onUpdate": "no action"
        }
      },
      "compositePrimaryKeys": {
        "role_to_permissions_role_id_permission_id_pk": {
          "name": "role_to_permissions_role_id_permission_id_pk",
          "columns": [
            "role_id",
            "permission_id"
          ]
        }
      },
      "uniqueConstraints": {},
      "policies": {},
      "checkConstraints": {},
      "isRLSEnabled": false
    },
    "public.products": {
      "name": "products",
      "schema": "",
      "columns": {
        "id": {
          "name": "id",
          "type": "uuid",
          "primaryKey": true,
          "notNull": true,
          "default": "gen_random_uuid()"
        },
        "code": {
          "name": "code",
          "type": "varchar(50)",
          "primaryKey": false,
          "notNull": true
        },
        "description": {
          "name": "description",
          "type": "varchar(255)",
          "primaryKey": false,
          "notNull": true
        },
        "price": {
          "name": "price",
          "type": "numeric",
          "primaryKey": false,
          "notNull": false
        },
        "category": {
          "name": "category",
          "type": "varchar(100)",
          "primaryKey": false,
          "notNull": false
        },
        "updated_at": {
          "name": "updated_at",
          "type": "timestamp",
          "primaryKey": false,
          "notNull": false
        },
        "created_at": {
          "name": "created_at",
          "type": "timestamp",
          "primaryKey": false,
          "notNull": true,
          "default": "now()"
        },
        "deleted_at": {
          "name": "deleted_at",
          "type": "timestamp",
          "primaryKey": false,
          "notNull": false
        }
      },
      "indexes": {
        "code_idx": {
          "name": "code_idx",
          "columns": [
            {
              "expression": "code",
              "isExpression": false,
              "asc": true,
              "nulls": "last"
            }
          ],
          "isUnique": false,
          "concurrently": false,
          "method": "btree",
          "with": {}
        }
      },
      "foreignKeys": {},
      "compositePrimaryKeys": {},
      "uniqueConstraints": {
        "code_unique": {
          "name": "code_unique",
          "nullsNotDistinct": false,
          "columns": [
            "code"
          ]
        }
      },
      "policies": {},
      "checkConstraints": {},
      "isRLSEnabled": false
    },
    "public.profiles": {
      "name": "profiles",
      "schema": "",
      "columns": {
        "id": {
          "name": "id",
          "type": "uuid",
          "primaryKey": true,
          "notNull": true
        },
        "username": {
          "name": "username",
          "type": "text",
          "primaryKey": false,
          "notNull": false
        },
        "full_name": {
          "name": "full_name",
          "type": "text",
          "primaryKey": false,
          "notNull": false
        },
        "avatar_url": {
          "name": "avatar_url",
          "type": "text",
          "primaryKey": false,
          "notNull": false
        },
        "website": {
          "name": "website",
          "type": "text",
          "primaryKey": false,
          "notNull": false
        },
        "updated_at": {
          "name": "updated_at",
          "type": "timestamp",
          "primaryKey": false,
          "notNull": false
        },
        "created_at": {
          "name": "created_at",
          "type": "timestamp",
          "primaryKey": false,
          "notNull": true,
          "default": "now()"
        },
        "deleted_at": {
          "name": "deleted_at",
          "type": "timestamp",
          "primaryKey": false,
          "notNull": false
        }
      },
      "indexes": {
        "username_idx": {
          "name": "username_idx",
          "columns": [
            {
              "expression": "username",
              "isExpression": false,
              "asc": true,
              "nulls": "last"
            }
          ],
          "isUnique": false,
          "concurrently": false,
          "method": "btree",
          "with": {}
        }
      },
      "foreignKeys": {
        "profiles_id_users_id_fk": {
          "name": "profiles_id_users_id_fk",
          "tableFrom": "profiles",
          "tableTo": "users",
          "schemaTo": "auth",
          "columnsFrom": [
            "id"
          ],
          "columnsTo": [
            "id"
          ],
          "onDelete": "cascade",
          "onUpdate": "no action"
        }
      },
      "compositePrimaryKeys": {},
      "uniqueConstraints": {
        "profiles_username_unique": {
          "name": "profiles_username_unique",
          "nullsNotDistinct": false,
          "columns": [
            "username"
          ]
        }
      },
      "policies": {},
      "checkConstraints": {
        "username_length": {
          "name": "username_length",
          "value": "LENGTH\n            (\n            \"profiles\".\"username\"\n            )\n            >=\n            3"
        }
      },
      "isRLSEnabled": false
    },
    "public.roles": {
      "name": "roles",
      "schema": "",
      "columns": {
        "id": {
          "name": "id",
          "type": "integer",
          "primaryKey": true,
          "notNull": true,
          "identity": {
            "type": "byDefault",
            "name": "roles_id_seq",
            "schema": "public",
            "increment": "1",
            "startWith": "1",
            "minValue": "1",
            "maxValue": "2147483647",
            "cache": "1",
            "cycle": false
          }
        },
        "role": {
          "name": "role",
          "type": "text",
          "primaryKey": false,
          "notNull": true
        }
      },
      "indexes": {},
      "foreignKeys": {},
      "compositePrimaryKeys": {},
      "uniqueConstraints": {
        "roles_role_unique": {
          "name": "roles_role_unique",
          "nullsNotDistinct": false,
          "columns": [
            "role"
          ]
        }
      },
      "policies": {},
      "checkConstraints": {},
      "isRLSEnabled": false
    },
    "public.users_to_roles": {
      "name": "users_to_roles",
      "schema": "",
      "columns": {
        "user_id": {
          "name": "user_id",
          "type": "uuid",
          "primaryKey": false,
          "notNull": true
        },
        "role_id": {
          "name": "role_id",
          "type": "integer",
          "primaryKey": false,
          "notNull": true
        }
      },
      "indexes": {},
      "foreignKeys": {
        "users_to_roles_user_id_users_id_fk": {
          "name": "users_to_roles_user_id_users_id_fk",
          "tableFrom": "users_to_roles",
          "tableTo": "users",
          "schemaTo": "auth",
          "columnsFrom": [
            "user_id"
          ],
          "columnsTo": [
            "id"
          ],
          "onDelete": "no action",
          "onUpdate": "no action"
        },
        "users_to_roles_role_id_roles_id_fk": {
          "name": "users_to_roles_role_id_roles_id_fk",
          "tableFrom": "users_to_roles",
          "tableTo": "roles",
          "columnsFrom": [
            "role_id"
          ],
          "columnsTo": [
            "id"
          ],
          "onDelete": "no action",
          "onUpdate": "no action"
        }
      },
      "compositePrimaryKeys": {
        "users_to_roles_user_id_role_id_pk": {
          "name": "users_to_roles_user_id_role_id_pk",
          "columns": [
            "user_id",
            "role_id"
          ]
        }
      },
      "uniqueConstraints": {},
      "policies": {},
      "checkConstraints": {},
      "isRLSEnabled": false
    },
    "public.seamstress": {
      "name": "seamstress",
      "schema": "",
      "columns": {
        "id": {
          "name": "id",
          "type": "uuid",
          "primaryKey": true,
          "notNull": true,
          "default": "gen_random_uuid()"
        },
        "internal_code": {
          "name": "internal_code",
          "type": "varchar(10)",
          "primaryKey": false,
          "notNull": true
        },
        "location_id": {
          "name": "location_id",
          "type": "uuid",
          "primaryKey": false,
          "notNull": true
        },
        "business_info_id": {
          "name": "business_info_id",
          "type": "uuid",
          "primaryKey": false,
          "notNull": true
        },
        "updated_at": {
          "name": "updated_at",
          "type": "timestamp",
          "primaryKey": false,
          "notNull": false
        },
        "created_at": {
          "name": "created_at",
          "type": "timestamp",
          "primaryKey": false,
          "notNull": true,
          "default": "now()"
        },
        "deleted_at": {
          "name": "deleted_at",
          "type": "timestamp",
          "primaryKey": false,
          "notNull": false
        }
      },
      "indexes": {},
      "foreignKeys": {
        "seamstress_location_id_locations_id_fk": {
          "name": "seamstress_location_id_locations_id_fk",
          "tableFrom": "seamstress",
          "tableTo": "locations",
          "columnsFrom": [
            "location_id"
          ],
          "columnsTo": [
            "id"
          ],
          "onDelete": "cascade",
          "onUpdate": "no action"
        },
        "seamstress_business_info_id_business_infos_id_fk": {
          "name": "seamstress_business_info_id_business_infos_id_fk",
          "tableFrom": "seamstress",
          "tableTo": "business_infos",
          "columnsFrom": [
            "business_info_id"
          ],
          "columnsTo": [
            "id"
          ],
          "onDelete": "cascade",
          "onUpdate": "no action"
        }
      },
      "compositePrimaryKeys": {},
      "uniqueConstraints": {
        "seamstress_internal_code_unique": {
          "name": "seamstress_internal_code_unique",
          "nullsNotDistinct": false,
          "columns": [
            "internal_code"
          ]
        }
      },
      "policies": {},
      "checkConstraints": {},
      "isRLSEnabled": false
    },
    "public.seamstress_to_users": {
      "name": "seamstress_to_users",
      "schema": "",
      "columns": {
        "seamstress_id": {
          "name": "seamstress_id",
          "type": "uuid",
          "primaryKey": false,
          "notNull": true
        },
        "user_id": {
          "name": "user_id",
          "type": "uuid",
          "primaryKey": false,
          "notNull": true
        }
      },
      "indexes": {},
      "foreignKeys": {
        "seamstress_to_users_seamstress_id_seamstress_id_fk": {
          "name": "seamstress_to_users_seamstress_id_seamstress_id_fk",
          "tableFrom": "seamstress_to_users",
          "tableTo": "seamstress",
          "columnsFrom": [
            "seamstress_id"
          ],
          "columnsTo": [
            "id"
          ],
          "onDelete": "cascade",
          "onUpdate": "no action"
        },
        "seamstress_to_users_user_id_users_id_fk": {
          "name": "seamstress_to_users_user_id_users_id_fk",
          "tableFrom": "seamstress_to_users",
          "tableTo": "users",
          "schemaTo": "auth",
          "columnsFrom": [
            "user_id"
          ],
          "columnsTo": [
            "id"
          ],
          "onDelete": "cascade",
          "onUpdate": "no action"
        }
      },
      "compositePrimaryKeys": {
        "seamstress_to_users_seamstress_id_user_id_pk": {
          "name": "seamstress_to_users_seamstress_id_user_id_pk",
          "columns": [
            "seamstress_id",
            "user_id"
          ]
        }
      },
      "uniqueConstraints": {},
      "policies": {},
      "checkConstraints": {},
      "isRLSEnabled": false
    },
    "public.shipment_items": {
      "name": "shipment_items",
      "schema": "",
      "columns": {
        "id": {
          "name": "id",
          "type": "uuid",
          "primaryKey": true,
          "notNull": true,
          "default": "gen_random_uuid()"
        },
        "shipment_id": {
          "name": "shipment_id",
          "type": "uuid",
          "primaryKey": false,
          "notNull": true
        },
        "product_id": {
          "name": "product_id",
          "type": "uuid",
          "primaryKey": false,
          "notNull": true
        },
        "unit_id": {
          "name": "unit_id",
          "type": "uuid",
          "primaryKey": false,
          "notNull": false
        },
        "quantity": {
          "name": "quantity",
          "type": "numeric",
          "primaryKey": false,
          "notNull": true
        },
        "unit_price": {
          "name": "unit_price",
          "type": "numeric",
          "primaryKey": false,
          "notNull": true
        },
        "total_price": {
          "name": "total_price",
          "type": "numeric",
          "primaryKey": false,
          "notNull": false,
          "generated": {
            "as": "\"shipment_items\".\"quantity\"\n            *\n            \"shipment_items\".\"unit_price\"",
            "type": "stored"
          }
        },
        "updated_at": {
          "name": "updated_at",
          "type": "timestamp",
          "primaryKey": false,
          "notNull": false
        },
        "created_at": {
          "name": "created_at",
          "type": "timestamp",
          "primaryKey": false,
          "notNull": true,
          "default": "now()"
        },
        "deleted_at": {
          "name": "deleted_at",
          "type": "timestamp",
          "primaryKey": false,
          "notNull": false
        }
      },
      "indexes": {
        "shipment_item_id_idx": {
          "name": "shipment_item_id_idx",
          "columns": [
            {
              "expression": "shipment_id",
              "isExpression": false,
              "asc": true,
              "nulls": "last"
            }
          ],
          "isUnique": false,
          "concurrently": false,
          "method": "btree",
          "with": {}
        },
        "shipment_item_product_id_idx": {
          "name": "shipment_item_product_id_idx",
          "columns": [
            {
              "expression": "product_id",
              "isExpression": false,
              "asc": true,
              "nulls": "last"
            }
          ],
          "isUnique": false,
          "concurrently": false,
          "method": "btree",
          "with": {}
        }
      },
      "foreignKeys": {
        "shipment_items_shipment_id_shipments_id_fk": {
          "name": "shipment_items_shipment_id_shipments_id_fk",
          "tableFrom": "shipment_items",
          "tableTo": "shipments",
          "columnsFrom": [
            "shipment_id"
          ],
          "columnsTo": [
            "id"
          ],
          "onDelete": "cascade",
          "onUpdate": "no action"
        },
        "shipment_items_product_id_products_id_fk": {
          "name": "shipment_items_product_id_products_id_fk",
          "tableFrom": "shipment_items",
          "tableTo": "products",
          "columnsFrom": [
            "product_id"
          ],
          "columnsTo": [
            "id"
          ],
          "onDelete": "no action",
          "onUpdate": "no action"
        },
        "shipment_items_unit_id_units_id_fk": {
          "name": "shipment_items_unit_id_units_id_fk",
          "tableFrom": "shipment_items",
          "tableTo": "units",
          "columnsFrom": [
            "unit_id"
          ],
          "columnsTo": [
            "id"
          ],
          "onDelete": "no action",
          "onUpdate": "no action"
        }
      },
      "compositePrimaryKeys": {},
      "uniqueConstraints": {},
      "policies": {},
      "checkConstraints": {},
      "isRLSEnabled": false
    },
    "public.units": {
      "name": "units",
      "schema": "",
      "columns": {
        "id": {
          "name": "id",
          "type": "uuid",
          "primaryKey": true,
          "notNull": true,
          "default": "gen_random_uuid()"
        },
        "unit_name": {
          "name": "unit_name",
          "type": "text",
          "primaryKey": false,
          "notNull": true
        }
      },
      "indexes": {
        "unit_name_idx": {
          "name": "unit_name_idx",
          "columns": [
            {
              "expression": "unit_name",
              "isExpression": false,
              "asc": true,
              "nulls": "last"
            }
          ],
          "isUnique": false,
          "concurrently": false,
          "method": "btree",
          "with": {}
        }
      },
      "foreignKeys": {},
      "compositePrimaryKeys": {},
      "uniqueConstraints": {},
      "policies": {},
      "checkConstraints": {},
      "isRLSEnabled": false
    },
    "public.shipments": {
      "name": "shipments",
      "schema": "",
      "columns": {
        "id": {
          "name": "id",
          "type": "uuid",
          "primaryKey": true,
          "notNull": true,
          "default": "gen_random_uuid()"
        },
        "number": {
          "name": "number",
          "type": "text",
          "primaryKey": false,
          "notNull": true
        },
        "access_key": {
          "name": "access_key",
          "type": "text",
          "primaryKey": false,
          "notNull": false
        },
        "series": {
          "name": "series",
          "type": "text",
          "primaryKey": false,
          "notNull": true
        },
        "type": {
          "name": "type",
          "type": "text",
          "primaryKey": false,
          "notNull": true
        },
        "authorization_protocol": {
          "name": "authorization_protocol",
          "type": "text",
          "primaryKey": false,
          "notNull": false
        },
        "issue_date": {
          "name": "issue_date",
          "type": "timestamp",
          "primaryKey": false,
          "notNull": true
        },
        "entry_exit_date": {
          "name": "entry_exit_date",
          "type": "timestamp",
          "primaryKey": false,
          "notNull": false
        },
        "entry_exit_time": {
          "name": "entry_exit_time",
          "type": "time",
          "primaryKey": false,
          "notNull": false
        },
        "recipient_id": {
          "name": "recipient_id",
          "type": "uuid",
          "primaryKey": false,
          "notNull": true
        },
        "financial_calc_id": {
          "name": "financial_calc_id",
          "type": "uuid",
          "primaryKey": false,
          "notNull": true
        },
        "transportation_type": {
          "name": "transportation_type",
          "type": "text",
          "primaryKey": false,
          "notNull": true,
          "default": "'1'"
        },
        "confirmed_at": {
          "name": "confirmed_at",
          "type": "timestamp",
          "primaryKey": false,
          "notNull": false
        },
        "delivered_at": {
          "name": "delivered_at",
          "type": "timestamp",
          "primaryKey": false,
          "notNull": false
        },
        "finished_at": {
          "name": "finished_at",
          "type": "timestamp",
          "primaryKey": false,
          "notNull": false
        },
        "collected_at": {
          "name": "collected_at",
          "type": "timestamp",
          "primaryKey": false,
          "notNull": false
        },
        "refused_at": {
          "name": "refused_at",
          "type": "timestamp",
          "primaryKey": false,
          "notNull": false
        },
        "archived_at": {
          "name": "archived_at",
          "type": "timestamp",
          "primaryKey": false,
          "notNull": false
        },
        "system_estimation": {
          "name": "system_estimation",
          "type": "timestamp",
          "primaryKey": false,
          "notNull": false
        },
        "informed_estimation": {
          "name": "informed_estimation",
          "type": "timestamp",
          "primaryKey": false,
          "notNull": false
        },
        "updated_at": {
          "name": "updated_at",
          "type": "timestamp",
          "primaryKey": false,
          "notNull": false
        },
        "created_at": {
          "name": "created_at",
          "type": "timestamp",
          "primaryKey": false,
          "notNull": true,
          "default": "now()"
        },
        "deleted_at": {
          "name": "deleted_at",
          "type": "timestamp",
          "primaryKey": false,
          "notNull": false
        }
      },
      "indexes": {
        "number_idx": {
          "name": "number_idx",
          "columns": [
            {
              "expression": "number",
              "isExpression": false,
              "asc": true,
              "nulls": "last"
            }
          ],
          "isUnique": false,
          "concurrently": false,
          "method": "btree",
          "with": {}
        },
        "access_key_idx": {
          "name": "access_key_idx",
          "columns": [
            {
              "expression": "access_key",
              "isExpression": false,
              "asc": true,
              "nulls": "last"
            }
          ],
          "isUnique": false,
          "concurrently": false,
          "method": "btree",
          "with": {}
        },
        "issue_date_idx": {
          "name": "issue_date_idx",
          "columns": [
            {
              "expression": "issue_date",
              "isExpression": false,
              "asc": true,
              "nulls": "last"
            }
          ],
          "isUnique": false,
          "concurrently": false,
          "method": "btree",
          "with": {}
        },
        "recipient_id_idx": {
          "name": "recipient_id_idx",
          "columns": [
            {
              "expression": "recipient_id",
              "isExpression": false,
              "asc": true,
              "nulls": "last"
            }
          ],
          "isUnique": false,
          "concurrently": false,
          "method": "btree",
          "with": {}
        },
        "shipments_confirmed_at_idx": {
          "name": "shipments_confirmed_at_idx",
          "columns": [
            {
              "expression": "confirmed_at",
              "isExpression": false,
              "asc": true,
              "nulls": "last"
            }
          ],
          "isUnique": false,
          "concurrently": false,
          "method": "btree",
          "with": {}
        },
        "shipments_delivered_at_idx": {
          "name": "shipments_delivered_at_idx",
          "columns": [
            {
              "expression": "delivered_at",
              "isExpression": false,
              "asc": true,
              "nulls": "last"
            }
          ],
          "isUnique": false,
          "concurrently": false,
          "method": "btree",
          "with": {}
        },
        "shipments_finished_at_idx": {
          "name": "shipments_finished_at_idx",
          "columns": [
            {
              "expression": "finished_at",
              "isExpression": false,
              "asc": true,
              "nulls": "last"
            }
          ],
          "isUnique": false,
          "concurrently": false,
          "method": "btree",
          "with": {}
        },
        "shipments_collected_at_idx": {
          "name": "shipments_collected_at_idx",
          "columns": [
            {
              "expression": "collected_at",
              "isExpression": false,
              "asc": true,
              "nulls": "last"
            }
          ],
          "isUnique": false,
          "concurrently": false,
          "method": "btree",
          "with": {}
        },
        "financial_calc_id_idx": {
          "name": "financial_calc_id_idx",
          "columns": [
            {
              "expression": "financial_calc_id",
              "isExpression": false,
              "asc": true,
              "nulls": "last"
            }
          ],
          "isUnique": false,
          "concurrently": false,
          "method": "btree",
          "with": {}
        }
      },
      "foreignKeys": {
        "shipments_recipient_id_seamstress_id_fk": {
          "name": "shipments_recipient_id_seamstress_id_fk",
          "tableFrom": "shipments",
          "tableTo": "seamstress",
          "columnsFrom": [
            "recipient_id"
          ],
          "columnsTo": [
            "id"
          ],
          "onDelete": "cascade",
          "onUpdate": "no action"
        },
        "shipments_financial_calc_id_financial_calculations_id_fk": {
          "name": "shipments_financial_calc_id_financial_calculations_id_fk",
          "tableFrom": "shipments",
          "tableTo": "financial_calculations",
          "columnsFrom": [
            "financial_calc_id"
          ],
          "columnsTo": [
            "id"
          ],
          "onDelete": "cascade",
          "onUpdate": "no action"
        }
      },
      "compositePrimaryKeys": {},
      "uniqueConstraints": {
        "shipments_access_key_unique": {
          "name": "shipments_access_key_unique",
          "nullsNotDistinct": false,
          "columns": [
            "access_key"
          ]
        }
      },
      "policies": {},
      "checkConstraints": {},
      "isRLSEnabled": false
    },
    "public.shipments_to_users": {
      "name": "shipments_to_users",
      "schema": "",
      "columns": {
        "shipment_id": {
          "name": "shipment_id",
          "type": "uuid",
          "primaryKey": false,
          "notNull": true
        },
        "user_id": {
          "name": "user_id",
          "type": "uuid",
          "primaryKey": false,
          "notNull": true
        }
      },
      "indexes": {},
      "foreignKeys": {
        "shipments_to_users_shipment_id_shipments_id_fk": {
          "name": "shipments_to_users_shipment_id_shipments_id_fk",
          "tableFrom": "shipments_to_users",
          "tableTo": "shipments",
          "columnsFrom": [
            "shipment_id"
          ],
          "columnsTo": [
            "id"
          ],
          "onDelete": "cascade",
          "onUpdate": "no action"
        },
        "shipments_to_users_user_id_users_id_fk": {
          "name": "shipments_to_users_user_id_users_id_fk",
          "tableFrom": "shipments_to_users",
          "tableTo": "users",
          "schemaTo": "auth",
          "columnsFrom": [
            "user_id"
          ],
          "columnsTo": [
            "id"
          ],
          "onDelete": "cascade",
          "onUpdate": "no action"
        }
      },
      "compositePrimaryKeys": {
        "shipments_to_users_shipment_id_user_id_pk": {
          "name": "shipments_to_users_shipment_id_user_id_pk",
          "columns": [
            "shipment_id",
            "user_id"
          ]
        }
      },
      "uniqueConstraints": {},
      "policies": {},
      "checkConstraints": {},
      "isRLSEnabled": false
    }
  },
  "enums": {},
  "schemas": {
    "auth": "auth"
  },
  "sequences": {},
  "roles": {},
  "policies": {},
  "views": {},
  "_meta": {
    "columns": {},
    "schemas": {},
    "tables": {}
  }
}